cloudmesh.rest-1.0.7-py2.7-nspkg.pth
cloudmesh/rest/__init__.py
cloudmesh/rest/elements.py
cloudmesh/rest/mongo.py
cloudmesh/rest/schema.py
cloudmesh/rest/service.py
cloudmesh/rest/settings.py
cloudmesh.rest-1.0.7.dist-info/DESCRIPTION.rst
cloudmesh.rest-1.0.7.dist-info/METADATA
cloudmesh.rest-1.0.7.dist-info/RECORD
cloudmesh.rest-1.0.7.dist-info/WHEEL
cloudmesh.rest-1.0.7.dist-info/metadata.json
cloudmesh.rest-1.0.7.dist-info/namespace_packages.txt
cloudmesh.rest-1.0.7.dist-info/top_level.txt
resources/__init__.py
resources/experimental/__init__.py
resources/experimental/schema-api.py
resources/experimental/schema-cmd.py
resources/experimental/specification/__init__.py
resources/experimental/test/__init__.py
resources/experimental/test/convert.py
tests/__init__.py
tests/test_mongo.py
