Metadata-Version: 2.0
Name: cloudmesh.rest
Version: 1.0.7
Summary: A command to manage eve and mongo locally
Home-page: https://github.com/cloudmesh/rest
Author: Gregor von Laszewski
Author-email: laszewski@gmail.com
License: Apache 2.0
Platform: UNKNOWN
Classifier: Development Status :: 5 - Production/Stable
Classifier: Environment :: Web Environment
Classifier: Intended Audience :: Developers
Classifier: License :: OSI Approved :: BSD License
Classifier: Operating System :: OS Independent
Classifier: Programming Language :: Python
Classifier: Programming Language :: Python :: 2
Classifier: Programming Language :: Python :: 3
Requires-Dist: coverage
Requires-Dist: detox
Requires-Dist: flake8
Requires-Dist: psutil
Requires-Dist: pygments
Requires-Dist: ruamel.yaml
Requires-Dist: tox
